cdmir/__init__.py
cdmir/datasets/__init__.py
cdmir/datasets/pgmdata.py
cdmir/datasets/simlulators.py
cdmir/datasets/utils.py
cdmir/discovery/__init__.py
cdmir/discovery/constraint/__init__.py
cdmir/discovery/constraint/adjacency_search.py
cdmir/discovery/constraint/pc.py
cdmir/discovery/constraint/PBSCM/PB_SCM.py
cdmir/discovery/constraint/PBSCM/__init__.py
cdmir/discovery/constraint/PBSCM/util.py
cdmir/discovery/constraint/PBSCM_PGF/CCARankTest.py
cdmir/discovery/constraint/PBSCM_PGF/PB_SCM_PGF.py
cdmir/discovery/constraint/PBSCM_PGF/__init__.py
cdmir/discovery/constraint/PBSCM_PGF/util.py
cdmir/discovery/funtional_based/__init__.py
cdmir/discovery/funtional_based/LearningHierarchicalStructure/GIN2.py
cdmir/discovery/funtional_based/LearningHierarchicalStructure/__init__.py
cdmir/discovery/funtional_based/LearningHierarchicalStructure/mutual.py
cdmir/discovery/funtional_based/LearningHierarchicalStructure/indTest/FisherTest.py
cdmir/discovery/funtional_based/LearningHierarchicalStructure/indTest/HSIC.py
cdmir/discovery/funtional_based/LearningHierarchicalStructure/indTest/HSIC2.py
cdmir/discovery/funtional_based/LearningHierarchicalStructure/indTest/HSICBlockTestObject.py
cdmir/discovery/funtional_based/LearningHierarchicalStructure/indTest/HSICPermutationTestObject.py
cdmir/discovery/funtional_based/LearningHierarchicalStructure/indTest/HSICSpectralTestObject.py
cdmir/discovery/funtional_based/LearningHierarchicalStructure/indTest/HSICTestObject.py
cdmir/discovery/funtional_based/LearningHierarchicalStructure/indTest/HSICtestImpure.py
cdmir/discovery/funtional_based/LearningHierarchicalStructure/indTest/TestObject.py
cdmir/discovery/funtional_based/LearningHierarchicalStructure/indTest/__init__.py
cdmir/discovery/funtional_based/LearningHierarchicalStructure/indTest/fastHSIC.py
cdmir/discovery/funtional_based/LearningHierarchicalStructure/indTest/independence.py
cdmir/discovery/funtional_based/SHP/Generate_Hawkes_data_from_tick.py
cdmir-0.1.1.dist-info/METADATA
cdmir-0.1.1.dist-info/WHEEL
cdmir-0.1.1.dist-info/top_level.txt
cdmir-0.1.1.dist-info/RECORD
