Metadata-Version: 2.4
Name: CDMIR
Version: 0.1.1
Summary: A pip package
Author: DMIRLab
License: GPL
Classifier: Operating System :: OS Independent
Classifier: Programming Language :: Python
Classifier: Programming Language :: Python :: 3.7
Classifier: Programming Language :: Python :: 3.8
Requires-Python: >=3.6
Requires-Dist: numpy
Requires-Dist: pandas
Requires-Dist: scipy>=1.7.3
Requires-Dist: scikit-learn
Requires-Dist: torch>=1.7.1
Requires-Dist: networkx
Requires-Dist: matplotlib
Dynamic: author
Dynamic: classifier
Dynamic: description
Dynamic: description-content-type
Dynamic: license
Dynamic: requires-dist
Dynamic: requires-python
Dynamic: summary
